kds_sms_server-3.3.0.dist-info/METADATA
kds_sms_server-3.3.0.dist-info/WHEEL
kds_sms_server-3.3.0.dist-info/entry_points.txt
kds_sms_server-3.3.0.dist-info/licenses/LICENSE
kds_sms_server/__init__.py
kds_sms_server/__main__.py
kds_sms_server/base.py
kds_sms_server/cli.py
kds_sms_server/db.py
kds_sms_server/gateways/__init__.py
kds_sms_server/gateways/config.py
kds_sms_server/gateways/gateway.py
kds_sms_server/gateways/teltonika/__init__.py
kds_sms_server/gateways/teltonika/config.py
kds_sms_server/gateways/teltonika/gateway.py
kds_sms_server/gateways/vonage/__init__.py
kds_sms_server/gateways/vonage/config.py
kds_sms_server/gateways/vonage/gateway.py
kds_sms_server/listener.py
kds_sms_server/server/__init__.py
kds_sms_server/server/api/__init__.py
kds_sms_server/server/api/config.py
kds_sms_server/server/api/server.py
kds_sms_server/server/config.py
kds_sms_server/server/file/__init__.py
kds_sms_server/server/file/config.py
kds_sms_server/server/file/server.py
kds_sms_server/server/server.py
kds_sms_server/server/tcp/__init__.py
kds_sms_server/server/tcp/config.py
kds_sms_server/server/tcp/server.py
kds_sms_server/server/ui/__init__.py
kds_sms_server/server/ui/config.py
kds_sms_server/server/ui/server.py
kds_sms_server/server/ui/templates/create.html
kds_sms_server/server/ui/templates/detail.html
kds_sms_server/server/ui/templates/layout.html
kds_sms_server/server/ui/templates/list.html
kds_sms_server/server/ui/templates/login.html
kds_sms_server/settings.py
kds_sms_server/statics/__init__.py
kds_sms_server/statics/favicon.ico
kds_sms_server/statics/logo.png
kds_sms_server/worker.py
kds_sms_server-3.3.0.dist-info/RECORD
