Metadata-Version: 2.1
Name: kds-sms-server
Version: 3.3.0
Summary: A broker server for sending SMS.
Author-Email: Julius Koenig <julius.koenig@kds-kg.de>
License:                     GNU GENERAL PUBLIC LICENSE
Requires-Python: >=3.11
Requires-Dist: typer>=0.16.0
Requires-Dist: chardet>=5.2.0
Requires-Dist: requests>=2.32.4
Requires-Dist: pythonping>=1.1.4
Requires-Dist: vonage>=4.4.3
Requires-Dist: python-multipart>=0.0.20
Requires-Dist: email-validator>=2.2.0
Requires-Dist: starlette-admin[i18n]>=0.15.1
Requires-Dist: pymysql>=1.1.1
Requires-Dist: itsdangerous>=2.2.0
Requires-Dist: wiederverwendbar[fastapi,sqlalchemy,typer,uvicorn]>=0.9.1
